LICENSE
README.md
setup.py
uiz/__init__.py
uiz/uiz.py
uiz.egg-info/PKG-INFO
uiz.egg-info/SOURCES.txt
uiz.egg-info/dependency_links.txt
uiz.egg-info/requires.txt
uiz.egg-info/top_level.txt