Metadata-Version: 2.1
Name: uiz
Version: 0.0.0
Summary: uiz is a simple user interface library
Home-page: https://github.com/zPointless/uiz
Author: PyModuleDev
Classifier: Development Status :: 3 - Alpha
Classifier: Intended Audience :: Developers
Classifier: License :: OSI Approved :: MIT License
Classifier: Programming Language :: Python :: 3
Classifier: Programming Language :: Python :: 3.6
Classifier: Programming Language :: Python :: 3.7
Classifier: Programming Language :: Python :: 3.8
Classifier: Programming Language :: Python :: 3.9
License-File: LICENSE
Requires-Dist: PyQt5
